verovio/__init__.py
verovio/_verovio.cp310-win_amd64.pyd
verovio/setup.py
verovio/verovio.py
verovio/data/Bravura.css
verovio/data/Bravura.xml
verovio/data/Gootville.css
verovio/data/Gootville.xml
verovio/data/Leipzig.css
verovio/data/Leipzig.xml
verovio/data/Leland.css
verovio/data/Leland.xml
verovio/data/Petaluma.css
verovio/data/Petaluma.xml
verovio/data/footer.svg
verovio/data/Bravura/0020.xml
verovio/data/Bravura/266D.xml
verovio/data/Bravura/266E.xml
verovio/data/Bravura/266F.xml
verovio/data/Bravura/E000.xml
verovio/data/Bravura/E003.xml
verovio/data/Bravura/E004.xml
verovio/data/Bravura/E043.xml
verovio/data/Bravura/E044.xml
verovio/data/Bravura/E045.xml
verovio/data/Bravura/E046.xml
verovio/data/Bravura/E047.xml
verovio/data/Bravura/E048.xml
verovio/data/Bravura/E049.xml
verovio/data/Bravura/E04A.xml
verovio/data/Bravura/E04B.xml
verovio/data/Bravura/E050.xml
verovio/data/Bravura/E051.xml
verovio/data/Bravura/E052.xml
verovio/data/Bravura/E053.xml
verovio/data/Bravura/E054.xml
verovio/data/Bravura/E055.xml
verovio/data/Bravura/E056.xml
verovio/data/Bravura/E05C.xml
verovio/data/Bravura/E05D.xml
verovio/data/Bravura/E062.xml
verovio/data/Bravura/E063.xml
verovio/data/Bravura/E064.xml
verovio/data/Bravura/E065.xml
verovio/data/Bravura/E066.xml
verovio/data/Bravura/E069.xml
verovio/data/Bravura/E06A.xml
verovio/data/Bravura/E06D.xml
verovio/data/Bravura/E06E.xml
verovio/data/Bravura/E073.xml
verovio/data/Bravura/E074.xml
verovio/data/Bravura/E075.xml
verovio/data/Bravura/E076.xml
verovio/data/Bravura/E077.xml
verovio/data/Bravura/E07A.xml
verovio/data/Bravura/E07B.xml
verovio/data/Bravura/E07C.xml
verovio/data/Bravura/E080.xml
verovio/data/Bravura/E081.xml
verovio/data/Bravura/E082.xml
verovio/data/Bravura/E083.xml
verovio/data/Bravura/E084.xml
verovio/data/Bravura/E085.xml
verovio/data/Bravura/E086.xml
verovio/data/Bravura/E087.xml
verovio/data/Bravura/E088.xml
verovio/data/Bravura/E089.xml
verovio/data/Bravura/E08A.xml
verovio/data/Bravura/E08B.xml
verovio-3.15.0.dist-info/COPYING
verovio-3.15.0.dist-info/COPYING.LESSER
verovio-3.15.0.dist-info/METADATA
verovio-3.15.0.dist-info/WHEEL
verovio-3.15.0.dist-info/top_level.txt
verovio-3.15.0.dist-info/RECORD
