Metadata-Version: 2.1
Name: verovio
Version: 3.15.0
Summary: A library and toolkit for engraving MEI music notation into SVG
Home-page: https://www.verovio.org
License: LGPLv3
Project-URL: Bug Reports, https://github.com/rism-digital/verovio/issues
Project-URL: Source, https://github.com/rism-digital/verovio
Platform: UNKNOWN
Classifier: License :: OSI Approved :: GNU Lesser General Public License v3 (LGPLv3)
Classifier: Programming Language :: Python :: 3
Classifier: Programming Language :: C++
Classifier: Operating System :: OS Independent
Requires-Python: >=3.7
License-File: COPYING
License-File: COPYING.LESSER
